jarvy/__init__.py
jarvy/actions.py
jarvy/settings.py
jarvy/packages/__init__.py
jarvy/packages/google/__init__.py
jarvy-1.2.5.dist-info/DESCRIPTION.rst
jarvy-1.2.5.dist-info/METADATA
jarvy-1.2.5.dist-info/metadata.json
jarvy-1.2.5.dist-info/pbr.json
jarvy-1.2.5.dist-info/RECORD
jarvy-1.2.5.dist-info/top_level.txt
jarvy-1.2.5.dist-info/WHEEL
