Metadata-Version: 2.0
Name: jarvy
Version: 1.2.5
Summary: Python Intelligent Assistant for Humans.
Home-page: http://github.com/jarvy/jarvy
Author: Semih Yagcioglu
Author-email: semihyagcioglu@yahoo.com
License: MIT
Platform: UNKNOWN
Classifier: Development Status :: 3 - Alpha
Classifier: Intended Audience :: Developers
Classifier: Natural Language :: English
Classifier: License :: OSI Approved :: MIT License
Classifier: Programming Language :: Python
Classifier: Programming Language :: Python :: 2.6
Classifier: Programming Language :: Python :: 2.7
Requires-Dist: beautifulsoup4
Requires-Dist: google
